{"nodes": [{"id": "users_zweaungnaing_developer_vibe_coding_clothing_prd_md", "label": "PRD.md", "file_type": "document", "source_file": "PRD.md", "source_location": "L1"}, {"id": "clothing_prd_prd_myanmar_local_brand_shirt_e_commerce_platform", "label": "PRD \u2014 Myanmar Local Brand Shirt E-Commerce Platform", "file_type": "document", "source_file": "PRD.md", "source_location": "L1"}, {"id": "clothing_prd_1_project_overview", "label": "1. Project Overview", "file_type": "document", "source_file": "PRD.md", "source_location": "L10"}, {"id": "clothing_prd_1_1_executive_summary", "label": "1.1 Executive Summary", "file_type": "document", "source_file": "PRD.md", "source_location": "L12"}, {"id": "clothing_prd_1_2_project_goals", "label": "1.2 Project Goals", "file_type": "document", "source_file": "PRD.md", "source_location": "L16"}, {"id": "clothing_prd_1_3_success_metrics", "label": "1.3 Success Metrics", "file_type": "document", "source_file": "PRD.md", "source_location": "L27"}, {"id": "clothing_prd_2_technology_stack_locked", "label": "2. Technology Stack (Locked)", "file_type": "document", "source_file": "PRD.md", "source_location": "L40"}, {"id": "clothing_prd_3_design_system_summary", "label": "3. Design System (Summary)", "file_type": "document", "source_file": "PRD.md", "source_location": "L72"}, {"id": "clothing_prd_3_1_single_unified_design_system", "label": "3.1 Single Unified Design System", "file_type": "document", "source_file": "PRD.md", "source_location": "L76"}, {"id": "clothing_prd_3_2_rtl_support", "label": "3.2 RTL Support", "file_type": "document", "source_file": "PRD.md", "source_location": "L85"}, {"id": "clothing_prd_3_3_cursor_behavior", "label": "3.3 Cursor Behavior", "file_type": "document", "source_file": "PRD.md", "source_location": "L92"}, {"id": "clothing_prd_4_monorepo_structure", "label": "4. Monorepo Structure", "file_type": "document", "source_file": "PRD.md", "source_location": "L98"}, {"id": "clothing_prd_4_1_sharing_rules", "label": "4.1 Sharing Rules", "file_type": "document", "source_file": "PRD.md", "source_location": "L153"}, {"id": "clothing_prd_5_environment_configuration", "label": "5. Environment & Configuration", "file_type": "document", "source_file": "PRD.md", "source_location": "L161"}, {"id": "clothing_prd_5_1_environment_variables", "label": "5.1 Environment Variables", "file_type": "document", "source_file": "PRD.md", "source_location": "L163"}, {"id": "clothing_prd_5_2_mcp_configuration", "label": "5.2 MCP Configuration", "file_type": "document", "source_file": "PRD.md", "source_location": "L193"}, {"id": "clothing_prd_5_3_prettier_configuration", "label": "5.3 Prettier Configuration", "file_type": "document", "source_file": "PRD.md", "source_location": "L208"}, {"id": "clothing_prd_6_data_models_convex_schema", "label": "6. Data Models (Convex Schema)", "file_type": "document", "source_file": "PRD.md", "source_location": "L238"}, {"id": "clothing_prd_6_1_users", "label": "6.1 users", "file_type": "document", "source_file": "PRD.md", "source_location": "L242"}, {"id": "clothing_prd_6_2_categories", "label": "6.2 categories", "file_type": "document", "source_file": "PRD.md", "source_location": "L256"}, {"id": "clothing_prd_6_3_products_with_embedded_variants", "label": "6.3 products (with EMBEDDED VARIANTS)", "file_type": "document", "source_file": "PRD.md", "source_location": "L274"}, {"id": "clothing_prd_6_4_cartitems", "label": "6.4 cartItems", "file_type": "document", "source_file": "PRD.md", "source_location": "L314"}, {"id": "clothing_prd_6_5_wishlistitems", "label": "6.5 wishlistItems", "file_type": "document", "source_file": "PRD.md", "source_location": "L330"}, {"id": "clothing_prd_6_6_orders_with_snapshot_items", "label": "6.6 orders (with snapshot items)", "file_type": "document", "source_file": "PRD.md", "source_location": "L343"}, {"id": "clothing_prd_6_7_storesettings_singleton", "label": "6.7 storeSettings (singleton)", "file_type": "document", "source_file": "PRD.md", "source_location": "L388"}, {"id": "clothing_prd_6_8_architecture_rationale", "label": "6.8 Architecture Rationale", "file_type": "document", "source_file": "PRD.md", "source_location": "L410"}, {"id": "clothing_prd_7_customer_storefront_feature_requirements", "label": "7. Customer Storefront \u2014 Feature Requirements", "file_type": "document", "source_file": "PRD.md", "source_location": "L431"}, {"id": "clothing_prd_7_1_navigation_and_header_p0", "label": "7.1 Navigation and Header (P0)", "file_type": "document", "source_file": "PRD.md", "source_location": "L433"}, {"id": "clothing_prd_7_2_homepage_p0_p1", "label": "7.2 Homepage (P0/P1)", "file_type": "document", "source_file": "PRD.md", "source_location": "L446"}, {"id": "clothing_prd_7_3_product_listing_page_p0", "label": "7.3 Product Listing Page (P0)", "file_type": "document", "source_file": "PRD.md", "source_location": "L456"}, {"id": "clothing_prd_7_4_product_detail_page_p0_p1", "label": "7.4 Product Detail Page (P0/P1)", "file_type": "document", "source_file": "PRD.md", "source_location": "L470"}, {"id": "clothing_prd_7_5_cart_and_checkout_p0_p1", "label": "7.5 Cart and Checkout (P0/P1)", "file_type": "document", "source_file": "PRD.md", "source_location": "L487"}, {"id": "clothing_prd_7_6_authentication_p0_p1_p2", "label": "7.6 Authentication (P0/P1/P2)", "file_type": "document", "source_file": "PRD.md", "source_location": "L501"}, {"id": "clothing_prd_8_delivery_and_payment_specifications", "label": "8. Delivery and Payment Specifications", "file_type": "document", "source_file": "PRD.md", "source_location": "L515"}, {"id": "clothing_prd_8_1_delivery_methods", "label": "8.1 Delivery Methods", "file_type": "document", "source_file": "PRD.md", "source_location": "L517"}, {"id": "clothing_prd_8_2_payment_methods", "label": "8.2 Payment Methods", "file_type": "document", "source_file": "PRD.md", "source_location": "L524"}, {"id": "clothing_prd_9_routes_and_page_map", "label": "9. Routes and Page Map", "file_type": "document", "source_file": "PRD.md", "source_location": "L533"}, {"id": "clothing_prd_9_1_storefront_routes", "label": "9.1 Storefront Routes", "file_type": "document", "source_file": "PRD.md", "source_location": "L535"}, {"id": "clothing_prd_9_2_admin_routes", "label": "9.2 Admin Routes", "file_type": "document", "source_file": "PRD.md", "source_location": "L553"}, {"id": "clothing_prd_10_admin_panel_feature_requirements", "label": "10. Admin Panel \u2014 Feature Requirements", "file_type": "document", "source_file": "PRD.md", "source_location": "L570"}, {"id": "clothing_prd_10_1_datatable_standards_every_list_page", "label": "10.1 DataTable Standards (every list page)", "file_type": "document", "source_file": "PRD.md", "source_location": "L572"}, {"id": "clothing_prd_10_2_admin_dashboard", "label": "10.2 Admin Dashboard", "file_type": "document", "source_file": "PRD.md", "source_location": "L587"}, {"id": "clothing_prd_10_3_order_management", "label": "10.3 Order Management", "file_type": "document", "source_file": "PRD.md", "source_location": "L605"}, {"id": "clothing_prd_10_4_product_management", "label": "10.4 Product Management", "file_type": "document", "source_file": "PRD.md", "source_location": "L617"}, {"id": "clothing_prd_10_5_inventory_control", "label": "10.5 Inventory Control", "file_type": "document", "source_file": "PRD.md", "source_location": "L637"}, {"id": "clothing_prd_10_6_user_management", "label": "10.6 User Management", "file_type": "document", "source_file": "PRD.md", "source_location": "L650"}, {"id": "clothing_prd_10_7_storefront_controls", "label": "10.7 Storefront Controls", "file_type": "document", "source_file": "PRD.md", "source_location": "L661"}, {"id": "clothing_prd_11_error_handling_monitoring_and_code_quality", "label": "11. Error Handling, Monitoring, and Code Quality", "file_type": "document", "source_file": "PRD.md", "source_location": "L670"}, {"id": "clothing_prd_11_1_sentry_integration", "label": "11.1 Sentry Integration", "file_type": "document", "source_file": "PRD.md", "source_location": "L672"}, {"id": "clothing_prd_11_2_coderabbit_automated_code_review", "label": "11.2 CodeRabbit Automated Code Review", "file_type": "document", "source_file": "PRD.md", "source_location": "L685"}, {"id": "clothing_prd_11_3_user_facing_error_states", "label": "11.3 User-Facing Error States", "file_type": "document", "source_file": "PRD.md", "source_location": "L695"}, {"id": "clothing_prd_12_non_functional_requirements", "label": "12. Non-Functional Requirements", "file_type": "document", "source_file": "PRD.md", "source_location": "L712"}, {"id": "clothing_prd_13_development_workflow_and_conventions", "label": "13. Development Workflow and Conventions", "file_type": "document", "source_file": "PRD.md", "source_location": "L732"}, {"id": "clothing_prd_13_1_branching", "label": "13.1 Branching", "file_type": "document", "source_file": "PRD.md", "source_location": "L736"}, {"id": "clothing_prd_13_2_commit_convention", "label": "13.2 Commit Convention", "file_type": "document", "source_file": "PRD.md", "source_location": "L746"}, {"id": "clothing_prd_13_3_pull_request_process", "label": "13.3 Pull Request Process", "file_type": "document", "source_file": "PRD.md", "source_location": "L760"}, {"id": "clothing_prd_13_4_bun_command_reference", "label": "13.4 Bun Command Reference", "file_type": "document", "source_file": "PRD.md", "source_location": "L771"}, {"id": "clothing_prd_14_milestones_and_delivery_phases", "label": "14. Milestones and Delivery Phases", "file_type": "document", "source_file": "PRD.md", "source_location": "L792"}, {"id": "clothing_prd_15_open_questions_and_decisions_required", "label": "15. Open Questions and Decisions Required", "file_type": "document", "source_file": "PRD.md", "source_location": "L805"}, {"id": "clothing_prd_16_out_of_scope_v1_0", "label": "16. Out of Scope (v1.0)", "file_type": "document", "source_file": "PRD.md", "source_location": "L820"}, {"id": "clothing_prd_17_document_set", "label": "17. Document Set", "file_type": "document", "source_file": "PRD.md", "source_location": "L836"}], "edges": [{"source": "users_zweaungnaing_developer_vibe_coding_clothing_prd_md", "target": "clothing_prd_prd_myanmar_local_brand_shirt_e_commerce_platform", "relation": "contains", "confidence": "EXTRACTED", "source_file": "PRD.md", "source_location": "L1", "weight": 1.0}, {"source": "clothing_prd_prd_myanmar_local_brand_shirt_e_commerce_platform", "target": "clothing_prd_1_project_overview", "relation": "contains", "confidence": "EXTRACTED", "source_file": "PRD.md", "source_location": "L10", "weight": 1.0}, {"source": "clothing_prd_1_project_overview", "target": "clothing_prd_1_1_executive_summary", "relation": "contains", "confidence": "EXTRACTED", "source_file": "PRD.md", "source_location": "L12", "weight": 1.0}, {"source": "clothing_prd_1_project_overview", "target": "clothing_prd_1_2_project_goals", "relation": "contains", "confidence": "EXTRACTED", "source_file": "PRD.md", "source_location": "L16", "weight": 1.0}, {"source": "clothing_prd_1_project_overview", "target": "clothing_prd_1_3_success_metrics", "relation": "contains", "confidence": "EXTRACTED", "source_file": "PRD.md", "source_location": "L27", "weight": 1.0}, {"source": "clothing_prd_prd_myanmar_local_brand_shirt_e_commerce_platform", "target": "clothing_prd_2_technology_stack_locked", "relation": "contains", "confidence": "EXTRACTED", "source_file": "PRD.md", "source_location": "L40", "weight": 1.0}, {"source": "clothing_prd_prd_myanmar_local_brand_shirt_e_commerce_platform", "target": "clothing_prd_3_design_system_summary", "relation": "contains", "confidence": "EXTRACTED", "source_file": "PRD.md", "source_location": "L72", "weight": 1.0}, {"source": "clothing_prd_3_design_system_summary", "target": "clothing_prd_3_1_single_unified_design_system", "relation": "contains", "confidence": "EXTRACTED", "source_file": "PRD.md", "source_location": "L76", "weight": 1.0}, {"source": "clothing_prd_3_design_system_summary", "target": "clothing_prd_3_2_rtl_support", "relation": "contains", "confidence": "EXTRACTED", "source_file": "PRD.md", "source_location": "L85", "weight": 1.0}, {"source": "clothing_prd_3_design_system_summary", "target": "clothing_prd_3_3_cursor_behavior", "relation": "contains", "confidence": "EXTRACTED", "source_file": "PRD.md", "source_location": "L92", "weight": 1.0}, {"source": "clothing_prd_prd_myanmar_local_brand_shirt_e_commerce_platform", "target": "clothing_prd_4_monorepo_structure", "relation": "contains", "confidence": "EXTRACTED", "source_file": "PRD.md", "source_location": "L98", "weight": 1.0}, {"source": "clothing_prd_4_monorepo_structure", "target": "clothing_prd_4_1_sharing_rules", "relation": "contains", "confidence": "EXTRACTED", "source_file": "PRD.md", "source_location": "L153", "weight": 1.0}, {"source": "clothing_prd_prd_myanmar_local_brand_shirt_e_commerce_platform", "target": "clothing_prd_5_environment_configuration", "relation": "contains", "confidence": "EXTRACTED", "source_file": "PRD.md", "source_location": "L161", "weight": 1.0}, {"source": "clothing_prd_5_environment_configuration", "target": "clothing_prd_5_1_environment_variables", "relation": "contains", "confidence": "EXTRACTED", "source_file": "PRD.md", "source_location": "L163", "weight": 1.0}, {"source": "clothing_prd_5_environment_configuration", "target": "clothing_prd_5_2_mcp_configuration", "relation": "contains", "confidence": "EXTRACTED", "source_file": "PRD.md", "source_location": "L193", "weight": 1.0}, {"source": "clothing_prd_5_environment_configuration", "target": "clothing_prd_5_3_prettier_configuration", "relation": "contains", "confidence": "EXTRACTED", "source_file": "PRD.md", "source_location": "L208", "weight": 1.0}, {"source": "clothing_prd_prd_myanmar_local_brand_shirt_e_commerce_platform", "target": "clothing_prd_6_data_models_convex_schema", "relation": "contains", "confidence": "EXTRACTED", "source_file": "PRD.md", "source_location": "L238", "weight": 1.0}, {"source": "clothing_prd_6_data_models_convex_schema", "target": "clothing_prd_6_1_users", "relation": "contains", "confidence": "EXTRACTED", "source_file": "PRD.md", "source_location": "L242", "weight": 1.0}, {"source": "clothing_prd_6_data_models_convex_schema", "target": "clothing_prd_6_2_categories", "relation": "contains", "confidence": "EXTRACTED", "source_file": "PRD.md", "source_location": "L256", "weight": 1.0}, {"source": "clothing_prd_6_data_models_convex_schema", "target": "clothing_prd_6_3_products_with_embedded_variants", "relation": "contains", "confidence": "EXTRACTED", "source_file": "PRD.md", "source_location": "L274", "weight": 1.0}, {"source": "clothing_prd_6_data_models_convex_schema", "target": "clothing_prd_6_4_cartitems", "relation": "contains", "confidence": "EXTRACTED", "source_file": "PRD.md", "source_location": "L314", "weight": 1.0}, {"source": "clothing_prd_6_data_models_convex_schema", "target": "clothing_prd_6_5_wishlistitems", "relation": "contains", "confidence": "EXTRACTED", "source_file": "PRD.md", "source_location": "L330", "weight": 1.0}, {"source": "clothing_prd_6_data_models_convex_schema", "target": "clothing_prd_6_6_orders_with_snapshot_items", "relation": "contains", "confidence": "EXTRACTED", "source_file": "PRD.md", "source_location": "L343", "weight": 1.0}, {"source": "clothing_prd_6_data_models_convex_schema", "target": "clothing_prd_6_7_storesettings_singleton", "relation": "contains", "confidence": "EXTRACTED", "source_file": "PRD.md", "source_location": "L388", "weight": 1.0}, {"source": "clothing_prd_6_data_models_convex_schema", "target": "clothing_prd_6_8_architecture_rationale", "relation": "contains", "confidence": "EXTRACTED", "source_file": "PRD.md", "source_location": "L410", "weight": 1.0}, {"source": "clothing_prd_prd_myanmar_local_brand_shirt_e_commerce_platform", "target": "clothing_prd_7_customer_storefront_feature_requirements", "relation": "contains", "confidence": "EXTRACTED", "source_file": "PRD.md", "source_location": "L431", "weight": 1.0}, {"source": "clothing_prd_7_customer_storefront_feature_requirements", "target": "clothing_prd_7_1_navigation_and_header_p0", "relation": "contains", "confidence": "EXTRACTED", "source_file": "PRD.md", "source_location": "L433", "weight": 1.0}, {"source": "clothing_prd_7_customer_storefront_feature_requirements", "target": "clothing_prd_7_2_homepage_p0_p1", "relation": "contains", "confidence": "EXTRACTED", "source_file": "PRD.md", "source_location": "L446", "weight": 1.0}, {"source": "clothing_prd_7_customer_storefront_feature_requirements", "target": "clothing_prd_7_3_product_listing_page_p0", "relation": "contains", "confidence": "EXTRACTED", "source_file": "PRD.md", "source_location": "L456", "weight": 1.0}, {"source": "clothing_prd_7_customer_storefront_feature_requirements", "target": "clothing_prd_7_4_product_detail_page_p0_p1", "relation": "contains", "confidence": "EXTRACTED", "source_file": "PRD.md", "source_location": "L470", "weight": 1.0}, {"source": "clothing_prd_7_customer_storefront_feature_requirements", "target": "clothing_prd_7_5_cart_and_checkout_p0_p1", "relation": "contains", "confidence": "EXTRACTED", "source_file": "PRD.md", "source_location": "L487", "weight": 1.0}, {"source": "clothing_prd_7_customer_storefront_feature_requirements", "target": "clothing_prd_7_6_authentication_p0_p1_p2", "relation": "contains", "confidence": "EXTRACTED", "source_file": "PRD.md", "source_location": "L501", "weight": 1.0}, {"source": "clothing_prd_prd_myanmar_local_brand_shirt_e_commerce_platform", "target": "clothing_prd_8_delivery_and_payment_specifications", "relation": "contains", "confidence": "EXTRACTED", "source_file": "PRD.md", "source_location": "L515", "weight": 1.0}, {"source": "clothing_prd_8_delivery_and_payment_specifications", "target": "clothing_prd_8_1_delivery_methods", "relation": "contains", "confidence": "EXTRACTED", "source_file": "PRD.md", "source_location": "L517", "weight": 1.0}, {"source": "clothing_prd_8_delivery_and_payment_specifications", "target": "clothing_prd_8_2_payment_methods", "relation": "contains", "confidence": "EXTRACTED", "source_file": "PRD.md", "source_location": "L524", "weight": 1.0}, {"source": "clothing_prd_prd_myanmar_local_brand_shirt_e_commerce_platform", "target": "clothing_prd_9_routes_and_page_map", "relation": "contains", "confidence": "EXTRACTED", "source_file": "PRD.md", "source_location": "L533", "weight": 1.0}, {"source": "clothing_prd_9_routes_and_page_map", "target": "clothing_prd_9_1_storefront_routes", "relation": "contains", "confidence": "EXTRACTED", "source_file": "PRD.md", "source_location": "L535", "weight": 1.0}, {"source": "clothing_prd_9_routes_and_page_map", "target": "clothing_prd_9_2_admin_routes", "relation": "contains", "confidence": "EXTRACTED", "source_file": "PRD.md", "source_location": "L553", "weight": 1.0}, {"source": "clothing_prd_prd_myanmar_local_brand_shirt_e_commerce_platform", "target": "clothing_prd_10_admin_panel_feature_requirements", "relation": "contains", "confidence": "EXTRACTED", "source_file": "PRD.md", "source_location": "L570", "weight": 1.0}, {"source": "clothing_prd_10_admin_panel_feature_requirements", "target": "clothing_prd_10_1_datatable_standards_every_list_page", "relation": "contains", "confidence": "EXTRACTED", "source_file": "PRD.md", "source_location": "L572", "weight": 1.0}, {"source": "clothing_prd_10_admin_panel_feature_requirements", "target": "clothing_prd_10_2_admin_dashboard", "relation": "contains", "confidence": "EXTRACTED", "source_file": "PRD.md", "source_location": "L587", "weight": 1.0}, {"source": "clothing_prd_10_admin_panel_feature_requirements", "target": "clothing_prd_10_3_order_management", "relation": "contains", "confidence": "EXTRACTED", "source_file": "PRD.md", "source_location": "L605", "weight": 1.0}, {"source": "clothing_prd_10_admin_panel_feature_requirements", "target": "clothing_prd_10_4_product_management", "relation": "contains", "confidence": "EXTRACTED", "source_file": "PRD.md", "source_location": "L617", "weight": 1.0}, {"source": "clothing_prd_10_admin_panel_feature_requirements", "target": "clothing_prd_10_5_inventory_control", "relation": "contains", "confidence": "EXTRACTED", "source_file": "PRD.md", "source_location": "L637", "weight": 1.0}, {"source": "clothing_prd_10_admin_panel_feature_requirements", "target": "clothing_prd_10_6_user_management", "relation": "contains", "confidence": "EXTRACTED", "source_file": "PRD.md", "source_location": "L650", "weight": 1.0}, {"source": "clothing_prd_10_admin_panel_feature_requirements", "target": "clothing_prd_10_7_storefront_controls", "relation": "contains", "confidence": "EXTRACTED", "source_file": "PRD.md", "source_location": "L661", "weight": 1.0}, {"source": "clothing_prd_prd_myanmar_local_brand_shirt_e_commerce_platform", "target": "clothing_prd_11_error_handling_monitoring_and_code_quality", "relation": "contains", "confidence": "EXTRACTED", "source_file": "PRD.md", "source_location": "L670", "weight": 1.0}, {"source": "clothing_prd_11_error_handling_monitoring_and_code_quality", "target": "clothing_prd_11_1_sentry_integration", "relation": "contains", "confidence": "EXTRACTED", "source_file": "PRD.md", "source_location": "L672", "weight": 1.0}, {"source": "clothing_prd_11_error_handling_monitoring_and_code_quality", "target": "clothing_prd_11_2_coderabbit_automated_code_review", "relation": "contains", "confidence": "EXTRACTED", "source_file": "PRD.md", "source_location": "L685", "weight": 1.0}, {"source": "clothing_prd_11_error_handling_monitoring_and_code_quality", "target": "clothing_prd_11_3_user_facing_error_states", "relation": "contains", "confidence": "EXTRACTED", "source_file": "PRD.md", "source_location": "L695", "weight": 1.0}, {"source": "clothing_prd_prd_myanmar_local_brand_shirt_e_commerce_platform", "target": "clothing_prd_12_non_functional_requirements", "relation": "contains", "confidence": "EXTRACTED", "source_file": "PRD.md", "source_location": "L712", "weight": 1.0}, {"source": "clothing_prd_prd_myanmar_local_brand_shirt_e_commerce_platform", "target": "clothing_prd_13_development_workflow_and_conventions", "relation": "contains", "confidence": "EXTRACTED", "source_file": "PRD.md", "source_location": "L732", "weight": 1.0}, {"source": "clothing_prd_13_development_workflow_and_conventions", "target": "clothing_prd_13_1_branching", "relation": "contains", "confidence": "EXTRACTED", "source_file": "PRD.md", "source_location": "L736", "weight": 1.0}, {"source": "clothing_prd_13_development_workflow_and_conventions", "target": "clothing_prd_13_2_commit_convention", "relation": "contains", "confidence": "EXTRACTED", "source_file": "PRD.md", "source_location": "L746", "weight": 1.0}, {"source": "clothing_prd_13_development_workflow_and_conventions", "target": "clothing_prd_13_3_pull_request_process", "relation": "contains", "confidence": "EXTRACTED", "source_file": "PRD.md", "source_location": "L760", "weight": 1.0}, {"source": "clothing_prd_13_development_workflow_and_conventions", "target": "clothing_prd_13_4_bun_command_reference", "relation": "contains", "confidence": "EXTRACTED", "source_file": "PRD.md", "source_location": "L771", "weight": 1.0}, {"source": "clothing_prd_prd_myanmar_local_brand_shirt_e_commerce_platform", "target": "clothing_prd_14_milestones_and_delivery_phases", "relation": "contains", "confidence": "EXTRACTED", "source_file": "PRD.md", "source_location": "L792", "weight": 1.0}, {"source": "clothing_prd_prd_myanmar_local_brand_shirt_e_commerce_platform", "target": "clothing_prd_15_open_questions_and_decisions_required", "relation": "contains", "confidence": "EXTRACTED", "source_file": "PRD.md", "source_location": "L805", "weight": 1.0}, {"source": "clothing_prd_prd_myanmar_local_brand_shirt_e_commerce_platform", "target": "clothing_prd_16_out_of_scope_v1_0", "relation": "contains", "confidence": "EXTRACTED", "source_file": "PRD.md", "source_location": "L820", "weight": 1.0}, {"source": "clothing_prd_prd_myanmar_local_brand_shirt_e_commerce_platform", "target": "clothing_prd_17_document_set", "relation": "contains", "confidence": "EXTRACTED", "source_file": "PRD.md", "source_location": "L836", "weight": 1.0}], "input_tokens": 0, "output_tokens": 0}